daemonprocessing/__config.py
daemonprocessing/__daemon.py
daemonprocessing/__init__.py
daemonprocessing/__log.py
daemonprocessing/rerun.py
daemonprocessing-0.1.3.dist-info/METADATA
daemonprocessing-0.1.3.dist-info/WHEEL
daemonprocessing-0.1.3.dist-info/RECORD
