Metadata-Version: 2.1
Name: daemonprocessing
Version: 0.1.3
Summary: cross-platform daemon
Author: jawide
Author-email: 596929059@qq.com
Requires-Python: >=3.7,<4.0
Classifier: Programming Language :: Python :: 3
Classifier: Programming Language :: Python :: 3.7
Classifier: Programming Language :: Python :: 3.8
Classifier: Programming Language :: Python :: 3.9
Classifier: Programming Language :: Python :: 3.10
Classifier: Programming Language :: Python :: 3.11
